skip_ssg/server.py
skip_ssg/skip.py
skip_ssg/sources.py
skip_ssg/watchers.py
skip_ssg-0.2.0.dist-info/entry_points.txt
skip_ssg-0.2.0.dist-info/LICENSE.txt
skip_ssg-0.2.0.dist-info/WHEEL
skip_ssg-0.2.0.dist-info/METADATA
skip_ssg-0.2.0.dist-info/RECORD
